pyadalight/__init__.py
pyadalight/__main__.py
pyadalight/adalight.py
pyadalight/main.py
pyadalight/singleton.py
pyadalight/utils.py
pyadalight-1.0.0b3.dist-info/LICENSE
pyadalight-1.0.0b3.dist-info/METADATA
pyadalight-1.0.0b3.dist-info/WHEEL
pyadalight-1.0.0b3.dist-info/entry_points.txt
pyadalight-1.0.0b3.dist-info/RECORD
